statuscope/__init__.py
statuscope/logger.py
statuscope-0.1.1.dist-info/LICENSE
statuscope-0.1.1.dist-info/METADATA
statuscope-0.1.1.dist-info/WHEEL
statuscope-0.1.1.dist-info/top_level.txt
statuscope-0.1.1.dist-info/RECORD
