Metadata-Version: 2.1
Name: statuscope
Version: 0.1.1
Summary: A package to ease log sending to Statuscope
Home-page: https://github.com/statuscope-io/python-package
Author: Baris Demiray
Author-email: baris.demiray@gmail.com
License: UNKNOWN
Platform: UNKNOWN
Classifier: Programming Language :: Python :: 3
Classifier: License :: OSI Approved :: MIT License
Classifier: Operating System :: OS Independent
Requires-Dist: requests
Requires-Dist: simplejson
